aodh/__init__.py
aodh/coordination.py
aodh/event.py
aodh/i18n.py
aodh/keystone_client.py
aodh/messaging.py
aodh/opts.py
aodh/profiler.py
aodh/queue.py
aodh/service.py
aodh/version.py
aodh/api/__init__.py
aodh/api/api-paste.ini
aodh/api/app.py
aodh/api/app.wsgi
aodh/api/hooks.py
aodh/api/middleware.py
aodh/api/policies.py
aodh/api/rbac.py
aodh/api/controllers/__init__.py
aodh/api/controllers/root.py
aodh/api/controllers/v2/__init__.py
aodh/api/controllers/v2/alarms.py
aodh/api/controllers/v2/base.py
aodh/api/controllers/v2/capabilities.py
aodh/api/controllers/v2/metrics.py
aodh/api/controllers/v2/query.py
aodh/api/controllers/v2/quotas.py
aodh/api/controllers/v2/root.py
aodh/api/controllers/v2/utils.py
aodh/api/controllers/v2/alarm_rules/__init__.py
aodh/api/controllers/v2/alarm_rules/composite.py
aodh/api/controllers/v2/alarm_rules/event.py
aodh/api/controllers/v2/alarm_rules/gnocchi.py
aodh/api/controllers/v2/alarm_rules/loadbalancer.py
aodh/api/controllers/v2/alarm_rules/prometheus.py
aodh/cmd/__init__.py
aodh/cmd/alarm.py
aodh/cmd/aodh-config-generator.conf
aodh/cmd/aodh-policy-generator.conf
aodh/cmd/status.py
aodh/cmd/storage.py
aodh/conf/__init__.py
aodh/conf/defaults.py
aodh/evaluator/__init__.py
aodh/evaluator/composite.py
aodh/evaluator/event.py
aodh/evaluator/gnocchi.py
aodh/evaluator/loadbalancer.py
aodh/evaluator/prometheus.py
aodh/evaluator/threshold.py
aodh/evaluator/utils.py
aodh/locale/de/LC_MESSAGES/aodh.po
aodh/locale/en_GB/LC_MESSAGES/aodh.po
aodh/locale/es/LC_MESSAGES/aodh.po
aodh/locale/fr/LC_MESSAGES/aodh.po
aodh/locale/id/LC_MESSAGES/aodh.po
aodh/locale/it/LC_MESSAGES/aodh.po
aodh/locale/ja/LC_MESSAGES/aodh.po
aodh/locale/ko_KR/LC_MESSAGES/aodh.po
aodh/locale/pt/LC_MESSAGES/aodh.po
aodh/locale/pt_BR/LC_MESSAGES/aodh.po
aodh/locale/ru/LC_MESSAGES/aodh.po
aodh/locale/zh_CN/LC_MESSAGES/aodh.po
aodh/locale/zh_TW/LC_MESSAGES/aodh.po
aodh/notifier/__init__.py
aodh/notifier/heat.py
aodh/notifier/log.py
aodh/notifier/rest.py
aodh/notifier/test.py
aodh-21.0.0.dist-info/AUTHORS
aodh-21.0.0.dist-info/LICENSE
aodh-21.0.0.dist-info/METADATA
aodh-21.0.0.dist-info/WHEEL
aodh-21.0.0.dist-info/entry_points.txt
aodh-21.0.0.dist-info/pbr.json
aodh-21.0.0.dist-info/top_level.txt
aodh-21.0.0.dist-info/RECORD
